pspsps/__init__.py
pspsps/http.py
pspsps/safebooru.py
pspsps/term.py
pspsps/terminyal.py
pspsps-0.2.5.data/scripts/pspsps
pspsps-0.2.5.dist-info/LICENSE
pspsps-0.2.5.dist-info/METADATA
pspsps-0.2.5.dist-info/WHEEL
pspsps-0.2.5.dist-info/top_level.txt
pspsps-0.2.5.dist-info/RECORD
