Metadata-Version: 2.1
Name: pspsps
Version: 0.2.5
Summary: Show catgirls from the Internet on the terminal
Home-page: https://github.com/melissaboiko/pspsps
Author: Melissa Boiko
Author-email: melissa@namakajiri.net
License: AGPLv3+
Platform: UNKNOWN
Classifier: License :: OSI Approved :: GNU Affero General Public License v3 or later (AGPLv3+)
Requires-Python: >=3.6.0
Requires-Dist: ascii-magic
Requires-Dist: climage
Requires-Dist: typing
Requires-Dist: typing-extensions
Provides-Extra: coloredlogs
Requires-Dist: coloredlogs ; extra == 'coloredlogs'
